notecode/AttentionDecoder.py
notecode/__init__.py
notecode/data/__init__.py
notecode/data/data.py
notecode/data/download.py
notecode/data/test.py
notecode-0.0.9.dist-info/METADATA
notecode-0.0.9.dist-info/WHEEL
notecode-0.0.9.dist-info/top_level.txt
notecode-0.0.9.dist-info/RECORD
