Metadata-Version: 2.1
Name: notecode
Version: 0.0.9
Summary: notecode
Home-page: https://github.com/1007530194
Author: euler
Author-email: 1007530194@qq.com
License: UNKNOWN
Platform: UNKNOWN
